astronomer/providers/venv/__init__.py
astronomer/providers/venv/decorators.py
astro_provider_venv-1.0.0a3.dist-info/LICENSE
astro_provider_venv-1.0.0a3.dist-info/METADATA
astro_provider_venv-1.0.0a3.dist-info/WHEEL
astro_provider_venv-1.0.0a3.dist-info/entry_points.txt
astro_provider_venv-1.0.0a3.dist-info/top_level.txt
astro_provider_venv-1.0.0a3.dist-info/RECORD
