Metadata-Version: 2.1
Name: astro-provider-venv
Version: 1.0.0a3
Summary: Easily create and use Python Virtualenvs in Apache Airflow
Author-email: Ash Berlin-Taylor <ash_github@firemirror.com>, Ian Buss <ian.buss@astronomer.io>, Kaxil Niak <kaxil@astronomer.io>
License: Apache License 2.0
Project-URL: Source, https://github.com/astronomer/astro-provider-venv
Classifier: Framework :: Apache Airflow
Classifier: Framework :: Apache Airflow :: Provider
Requires-Python: ~=3.7
License-File: LICENSE
Requires-Dist: apache-airflow (>=2.4)
Provides-Extra: tests
Requires-Dist: pytest (>=7.0) ; extra == 'tests'
